augmentedbondingcurve/__init__.py
augmentedbondingcurve/model.py
ltf_abcm-0.0.2.dist-info/LICENSE
ltf_abcm-0.0.2.dist-info/METADATA
ltf_abcm-0.0.2.dist-info/WHEEL
ltf_abcm-0.0.2.dist-info/top_level.txt
ltf_abcm-0.0.2.dist-info/RECORD
